html2md/__init__.py
html2md/__main__.py
html2md/convert.py
html2md/convert_test.py
html2md/html2md.py
html2md/html2md_test.py
html2md-0.1.7.dist-info/LICENSE
html2md-0.1.7.dist-info/METADATA
html2md-0.1.7.dist-info/WHEEL
html2md-0.1.7.dist-info/entry_points.txt
html2md-0.1.7.dist-info/top_level.txt
html2md-0.1.7.dist-info/RECORD
