Metadata-Version: 2.1
Name: html2md
Version: 0.1.7
Summary: HTML to Markdown converter.
Home-page: https://github.com/davidcavazos/html2md
Author: David Cavazos
Author-email: dcavazosw@gmail.com
License: UNKNOWN
Platform: UNKNOWN
Classifier: Development Status :: 3 - Alpha
Classifier: Intended Audience :: Developers
Classifier: License :: OSI Approved :: Apache Software License
Classifier: Operating System :: OS Independent
Classifier: Programming Language :: Python :: 2.7
Classifier: Programming Language :: Python :: 3
Classifier: Topic :: Software Development :: Build Tools
Classifier: Topic :: Software Development :: Code Generators
Classifier: Topic :: Software Development :: Compilers
Requires-Dist: pyquery
